pxpowershell/__init__.py
pxpowershell/example_dir2iso.py
pxpowershell/pxpowershell.py
pxpowershell-1.0.0.dist-info/METADATA
pxpowershell-1.0.0.dist-info/WHEEL
pxpowershell-1.0.0.dist-info/entry_points.txt
pxpowershell-1.0.0.dist-info/top_level.txt
pxpowershell-1.0.0.dist-info/RECORD
