Metadata-Version: 2.1
Name: pxpowershell
Version: 1.0.0
Summary: Interact with Powershell from Python
Home-page: https://github.com/markbaggett/pxpowershell
Author: MarkBaggett
Author-email: lo127001@gmail.com
License: GNU General Public License v3 (GPLv3
Platform: UNKNOWN
Classifier: Programming Language :: Python :: 3
Classifier: License :: OSI Approved :: GNU General Public License v3 (GPLv3)
Classifier: Operating System :: OS Independent
Requires-Python: >=3.6
Requires-Dist: pexpect (>=4.8.0)
